[
  {
    "id": "3a3b3d18-ee0c-43b6-880f-2fef9cdb609f",
    "sentence": "In view of realized and expected labor market conditions and inflation, the Committee decided to maintain the target range for the federal funds rate at 1-1/4 to 1‑1/2 percent.",
    "source": "statement_20180131.txt",
    "doc_type": "statement",
    "date": "2018-01-31",
    "context_question": null,
    "top": "",
    "sen": "",
    "ten": "",
    "hor": "",
    "com": "",
    "ris": "",
    "wid": ""
  },
  {
    "id": "e43c0f11-f087-467d-8c04-7e85c1566a3f",
    "sentence": "Hurricane-related disruptions and rebuilding have affected economic activity, employment, and inflation in recent months but have not materially altered the outlook for the national economy. Consequently, the Committee continues to expect that, with gradual adjustments in the stance of monetary policy, economic activity will expand at a moderate pace and labor market conditions will remain strong.",
    "source": "statement_20171213.txt",
    "doc_type": "statement",
    "date": "2017-12-13",
    "context_question": null,
    "top": "",
    "sen": "",
    "ten": "",
    "hor": "",
    "com": "",
    "ris": "",
    "wid": ""
  },
  {
    "id": "66175c96-e6c7-42da-a7c9-150d2a0ee26a",
    "sentence": "These arrangements will now provide dollars in amounts of up to $30 billion and $6 billion to the ECB and the SNB, respectively, representing increases of $10 billion and $2 billion. The FOMC extended the term of these swap lines through September 30, 2008. The actions announced today supplement the measures announced by the Federal Reserve on Friday to boost the size of the Term Auction Facility to $100 billion and to undertake a series of term repurchase transactions that will cumulate to $100 billion.",
    "source": "statement_20080311.txt",
    "doc_type": "statement",
    "date": "2008-03-11",
    "context_question": null,
    "top": "",
    "sen": "",
    "ten": "",
    "hor": "",
    "com": "",
    "ris": "",
    "wid": ""
  },
  {
    "id": "4db66646-9d5a-4441-aecc-cdb2970e16eb",
    "sentence": "The Committee sees the risks to the outlook for economic activity and the labor market as nearly balanced.",
    "source": "statement_20141217.txt",
    "doc_type": "statement",
    "date": "2014-12-17",
    "context_question": null,
    "top": "",
    "sen": "",
    "ten": "",
    "hor": "",
    "com": "",
    "ris": "",
    "wid": ""
  },
  {
    "id": "9af25462-8f91-4409-9d17-4b2cdf36ef3a",
    "sentence": "The Committee will continue to monitor the economic outlook and financial developments and will employ its policy tools as necessary to promote economic recovery and price stability.",
    "source": "statement_20100623.txt",
    "doc_type": "statement",
    "date": "2010-06-23",
    "context_question": null,
    "top": "",
    "sen": "",
    "ten": "",
    "hor": "",
    "com": "",
    "ris": "",
    "wid": ""
  },
  {
    "id": "386fa20c-094f-4645-b494-bcad249874a3",
    "sentence": "Central banks will continue to work together closely as needed to address pressures in funding markets.",
    "source": "statement_20100509.txt",
    "doc_type": "statement",
    "date": "2010-05-09",
    "context_question": null,
    "top": "",
    "sen": "",
    "ten": "",
    "hor": "",
    "com": "",
    "ris": "",
    "wid": ""
  },
  {
    "id": "2c123a0d-f0f1-4b5b-b5fd-d33e6f5e114d",
    "sentence": "Uncertainty about the economic outlook remains elevated. The Committee is attentive to the risks to both sides of its dual mandate and judges that downside risks to employment have risen.",
    "source": "statement_20250917.txt",
    "doc_type": "statement",
    "date": "2025-09-17",
    "context_question": null,
    "top": "",
    "sen": "",
    "ten": "",
    "hor": "",
    "com": "",
    "ris": "",
    "wid": ""
  },
  {
    "id": "a723b924-374e-488e-b006-87d02f6fff85",
    "sentence": "The Committee will continue to monitor the economic outlook and financial developments and will employ its policy tools as necessary to promote economic recovery and price stability. Accordingly, he believed that continuing to express the expectation of exceptionally low levels of the federal funds rate for an extended period was no longer warranted and limits the Committee's ability to adjust policy when needed. In addition, given economic and financial conditions, Mr. Hoenig did not believe that keeping constant the size of the Federal Reserve's holdings of longer-term securities at their current level was required to support a return to the Committee's policy objectives.",
    "source": "statement_20100810.txt",
    "doc_type": "statement",
    "date": "2010-08-10",
    "context_question": null,
    "top": "",
    "sen": "",
    "ten": "",
    "hor": "",
    "com": "",
    "ris": "",
    "wid": ""
  },
  {
    "id": "4e2797a0-f982-4f20-8071-0461b497baec",
    "sentence": "To support continued progress toward maximum employment and price stability, the Committee today reaffirmed its view that the current 0 to 1/4 percent target range for the federal funds rate remains appropriate. In determining how long to maintain this target range, the Committee will assess progress--both realized and expected--toward its objectives of maximum employment and 2 percent inflation. This assessment will take into account a wide range of information, including measures of labor market conditions, indicators of inflation pressures and inflation expectations, and readings on financial and international developments.",
    "source": "statement_20150917.txt",
    "doc_type": "statement",
    "date": "2015-09-17",
    "context_question": null,
    "top": "",
    "sen": "",
    "ten": "",
    "hor": "",
    "com": "",
    "ris": "",
    "wid": ""
  },
  {
    "id": "dca4f951-015b-4ceb-a4f7-b9ab1ce5344e",
    "sentence": "The Committee is maintaining its existing policies of reinvesting principal payments from its holdings of agency debt and agency mortgage-backed securities in agency mortgage-backed securities and of rolling over maturing Treasury securities at auction. The Committee will regularly review the size and composition of its securities holdings and is prepared to adjust those holdings as appropriate.",
    "source": "statement_20111213.txt",
    "doc_type": "statement",
    "date": "2011-12-13",
    "context_question": null,
    "top": "",
    "sen": "",
    "ten": "",
    "hor": "",
    "com": "",
    "ris": "",
    "wid": ""
  },
  {
    "id": "5e298ad2-b64f-4060-b9d5-4ae8e5cf0282",
    "sentence": "In a related action, the Board of Governors unanimously approved a 50-basis-point decrease in the discount rate to 5-1/4 percent. In taking this action, the Board approved the requests submitted by the Boards of Directors of the Federal Reserve Banks of Boston, New York, Cleveland, St. Louis, Minneapolis, Kansas City, and San Francisco.",
    "source": "statement_20070918.txt",
    "doc_type": "statement",
    "date": "2007-09-18",
    "context_question": null,
    "top": "",
    "sen": "",
    "ten": "",
    "hor": "",
    "com": "",
    "ris": "",
    "wid": ""
  },
  {
    "id": "e0b9f466-d0fc-4e03-a850-041af706b0fb",
    "sentence": "The Committee's assessments will take into account a wide range of information, including readings on labor market conditions, inflation pressures and inflation expectations, and financial and international developments.",
    "source": "statement_20251210.txt",
    "doc_type": "statement",
    "date": "2025-12-10",
    "context_question": null,
    "top": "",
    "sen": "",
    "ten": "",
    "hor": "",
    "com": "",
    "ris": "",
    "wid": ""
  },
  {
    "id": "11ef489c-b86f-435e-815e-e0abac14e094",
    "sentence": "The Federal Reserve will employ all available tools to promote the resumption of sustainable economic growth and to preserve price stability. The focus of the Committee's policy is to support the functioning of financial markets and stimulate the economy through open market operations and other measures that are likely to keep the size of the Federal Reserve's balance sheet at a high level. The Federal Reserve continues to purchase large quantities of agency debt and mortgage-backed securities to provide support to the mortgage and housing markets, and it stands ready to expand the quantity of such purchases and the duration of the purchase program as conditions warrant.",
    "source": "statement_20090128.txt",
    "doc_type": "statement",
    "date": "2009-01-28",
    "context_question": null,
    "top": "",
    "sen": "",
    "ten": "",
    "hor": "",
    "com": "",
    "ris": "",
    "wid": ""
  },
  {
    "id": "41ccfe32-570d-448a-9725-fe4b0d886008",
    "sentence": "The Committee will continue to evaluate the timing and overall amounts of its purchases of securities in light of the evolving economic outlook and conditions in financial markets. In light of ongoing improvements in the functioning of financial markets, the Committee and the Board of Governors anticipate that most of the Federal Reserve’s special liquidity facilities will expire on February 1, 2010, consistent with the Federal Reserve’s announcement of June 25, 2009. These facilities include the Asset-Backed Commercial Paper Money Market Mutual Fund Liquidity Facility, the Commercial Paper Funding Facility, the Primary Dealer Credit Facility, and the Term Securities Lending Facility.",
    "source": "statement_20091216.txt",
    "doc_type": "statement",
    "date": "2009-12-16",
    "context_question": null,
    "top": "",
    "sen": "",
    "ten": "",
    "hor": "",
    "com": "",
    "ris": "",
    "wid": ""
  },
  {
    "id": "a692efbc-f122-4fb5-9339-66edc00d41f0",
    "sentence": "The Committee is maintaining its existing policies of reinvesting principal payments from its holdings of agency debt and agency mortgage-backed securities in agency mortgage-backed securities and of rolling over maturing Treasury securities at auction. The Committee will regularly review the size and composition of its securities holdings and is prepared to adjust those holdings as appropriate to promote a stronger economic recovery in a context of price stability.",
    "source": "statement_20120425.txt",
    "doc_type": "statement",
    "date": "2012-04-25",
    "context_question": null,
    "top": "",
    "sen": "",
    "ten": "",
    "hor": "",
    "com": "",
    "ris": "",
    "wid": ""
  },
  {
    "id": "59ab2834-0f1c-4fd1-a4c4-5d834514658c",
    "sentence": "The Committee will act in a timely manner as needed to promote sustainable economic growth and price stability.",
    "source": "statement_20080318.txt",
    "doc_type": "statement",
    "date": "2008-03-18",
    "context_question": null,
    "top": "",
    "sen": "",
    "ten": "",
    "hor": "",
    "com": "",
    "ris": "",
    "wid": ""
  },
  {
    "id": "6be3aa4f-860e-4072-bc90-0e504b249f88",
    "sentence": "A range of recent indicators, including strong job gains, points to additional strengthening of the labor market.",
    "source": "statement_20160316.txt",
    "doc_type": "statement",
    "date": "2016-03-16",
    "context_question": null,
    "top": "",
    "sen": "",
    "ten": "",
    "hor": "",
    "com": "",
    "ris": "",
    "wid": ""
  },
  {
    "id": "f2ac6afe-1035-4f10-8b85-9e48065ead7c",
    "sentence": "In view of realized and expected labor market conditions and inflation, the Committee decided to maintain the target range for the federal funds rate at 1 to 1-1/4 percent.",
    "source": "statement_20171101.txt",
    "doc_type": "statement",
    "date": "2017-11-01",
    "context_question": null,
    "top": "",
    "sen": "",
    "ten": "",
    "hor": "",
    "com": "",
    "ris": "",
    "wid": ""
  },
  {
    "id": "376fcca4-9bcb-4e47-9f7a-3c6e6ef5cd70",
    "sentence": "The Committee anticipates that it will be appropriate to raise the target range for the federal funds rate when it has seen further improvement in the labor market and is reasonably confident that inflation will move back to its 2 percent objective over the medium term.",
    "source": "statement_20150617.txt",
    "doc_type": "statement",
    "date": "2015-06-17",
    "context_question": null,
    "top": "",
    "sen": "",
    "ten": "",
    "hor": "",
    "com": "",
    "ris": "",
    "wid": ""
  },
  {
    "id": "2a720069-7dd2-4afd-938b-01b59c5afdc4",
    "sentence": "Beginning in October, the Committee will add to its holdings of agency mortgage-backed securities at a pace of $5 billion per month rather than $10 billion per month, and will add to its holdings of longer-term Treasury securities at a pace of $10 billion per month rather than $15 billion per month.",
    "source": "statement_20140917.txt",
    "doc_type": "statement",
    "date": "2014-09-17",
    "context_question": null,
    "top": "",
    "sen": "",
    "ten": "",
    "hor": "",
    "com": "",
    "ris": "",
    "wid": ""
  },
  {
    "id": "456c9b53-52ff-4d3d-8640-efd6967c6240",
    "sentence": "In addition, the temporary liquidity swap arrangements between the Federal Reserve and other central banks will expire on February 1.",
    "source": "statement_20100127.txt",
    "doc_type": "statement",
    "date": "2010-01-27",
    "context_question": null,
    "top": "",
    "sen": "",
    "ten": "",
    "hor": "",
    "com": "",
    "ris": "",
    "wid": ""
  },
  {
    "id": "511f86b0-0cd8-44f6-a37c-18e6394826f5",
    "sentence": "In a related action, the Board of Governors unanimously approved a 25-basis-point decrease in the discount rate to 4-3/4 percent. In taking this action, the Board approved the requests submitted by the Boards of Directors of the Federal Reserve Banks of New York, Philadelphia, Cleveland, Richmond, Atlanta, Chicago, and St. Louis.",
    "source": "statement_20071211.txt",
    "doc_type": "statement",
    "date": "2007-12-11",
    "context_question": null,
    "top": "",
    "sen": "",
    "ten": "",
    "hor": "",
    "com": "",
    "ris": "",
    "wid": ""
  },
  {
    "id": "c6307d52-e9a5-4ddf-9972-82f82626b706",
    "sentence": "Job gains have slowed this year, and the unemployment rate has edged up but remained low through August; more recent indicators are consistent with these developments.",
    "source": "statement_20251029.txt",
    "doc_type": "statement",
    "date": "2025-10-29",
    "context_question": null,
    "top": "",
    "sen": "",
    "ten": "",
    "hor": "",
    "com": "",
    "ris": "",
    "wid": ""
  },
  {
    "id": "9f1f51ce-7708-4c41-b767-c5fd31850e36",
    "sentence": "In light of inflation developments and the further improvement in the labor market, the Committee decided to reduce the monthly pace of its net asset purchases by $20 billion for Treasury securities and $10 billion for agency mortgage-backed securities.",
    "source": "statement_20211215.txt",
    "doc_type": "statement",
    "date": "2021-12-15",
    "context_question": null,
    "top": "",
    "sen": "",
    "ten": "",
    "hor": "",
    "com": "",
    "ris": "",
    "wid": ""
  },
  {
    "id": "35ec1c6e-89be-44c1-b59c-0229abe118f6",
    "sentence": "The extent and timing of any additional firming that may be needed to address these risks will depend on the evolution of the outlook for both inflation and economic growth, as implied by incoming information.",
    "source": "statement_20070131.txt",
    "doc_type": "statement",
    "date": "2007-01-31",
    "context_question": null,
    "top": "",
    "sen": "",
    "ten": "",
    "hor": "",
    "com": "",
    "ris": "",
    "wid": ""
  },
  {
    "id": "798e0d1d-8d24-44d9-84e4-da2fa54f477e",
    "sentence": "The Committee decided to conclude the reduction of its aggregate securities holdings on December 1.",
    "source": "statement_20251029.txt",
    "doc_type": "statement",
    "date": "2025-10-29",
    "context_question": null,
    "top": "",
    "sen": "",
    "ten": "",
    "hor": "",
    "com": "",
    "ris": "",
    "wid": ""
  },
  {
    "id": "8e6400e1-0da2-4080-a972-693dec718b09",
    "sentence": "The Committee intends to purchase, by the end of June 2012, $400 billion of Treasury securities with remaining maturities of 6 years to 30 years and to sell an equal amount of Treasury securities with remaining maturities of 3 years or less. This program should put downward pressure on longer-term interest rates and help make broader financial conditions more accommodative. The Committee will regularly review the size and composition of its securities holdings and is prepared to adjust those holdings as appropriate.",
    "source": "statement_20110921.txt",
    "doc_type": "statement",
    "date": "2011-09-21",
    "context_question": null,
    "top": "",
    "sen": "",
    "ten": "",
    "hor": "",
    "com": "",
    "ris": "",
    "wid": ""
  },
  {
    "id": "65f27986-271e-405c-b368-a70c896e2878",
    "sentence": "In addition, the Open Market Desk will continue to offer large-scale overnight and term repurchase agreement operations.",
    "source": "statement_20200729.txt",
    "doc_type": "statement",
    "date": "2020-07-29",
    "context_question": null,
    "top": "",
    "sen": "",
    "ten": "",
    "hor": "",
    "com": "",
    "ris": "",
    "wid": ""
  },
  {
    "id": "fac2bf13-e730-4de1-a3bb-78cc18f78d96",
    "sentence": "In support of its goals, the Committee decided to lower the target range for the federal funds rate by 1/4 percentage point to 4-1/4 to 4-1/2 percent.",
    "source": "statement_20241218.txt",
    "doc_type": "statement",
    "date": "2024-12-18",
    "context_question": null,
    "top": "",
    "sen": "",
    "ten": "",
    "hor": "",
    "com": "",
    "ris": "",
    "wid": ""
  },
  {
    "id": "544150bb-73f6-49f1-831d-a7ab8fe6ff06",
    "sentence": "The Committee will regularly review the size and composition of its securities holdings in light of incoming information and is prepared to adjust those holdings as needed to best foster maximum employment and price stability.",
    "source": "statement_20110427.txt",
    "doc_type": "statement",
    "date": "2011-04-27",
    "context_question": null,
    "top": "",
    "sen": "",
    "ten": "",
    "hor": "",
    "com": "",
    "ris": "",
    "wid": ""
  },
  {
    "id": "90deda77-ac56-4b8f-ae01-d05687a98259",
    "sentence": "In support of its goals and in light of the shift in the balance of risks, the Committee decided to lower the target range for the federal funds rate by 1/4 percentage point to 3-3/4 to 4 percent.",
    "source": "statement_20251029.txt",
    "doc_type": "statement",
    "date": "2025-10-29",
    "context_question": null,
    "top": "",
    "sen": "",
    "ten": "",
    "hor": "",
    "com": "",
    "ris": "",
    "wid": ""
  },
  {
    "id": "8ac7b0b7-6fe6-437a-9acf-fa9f7a9be48c",
    "sentence": "The Committee sees the risks to the outlook for the economy and the labor market as nearly balanced. The Committee recognizes that inflation persistently below its 2 percent objective could pose risks to economic performance, and it is monitoring inflation developments carefully for evidence that inflation will move back toward its objective over the medium term.",
    "source": "statement_20140618.txt",
    "doc_type": "statement",
    "date": "2014-06-18",
    "context_question": null,
    "top": "",
    "sen": "",
    "ten": "",
    "hor": "",
    "com": "",
    "ris": "",
    "wid": ""
  },
  {
    "id": "eea6b596-689d-4f1d-b9c0-226fc6fa6430",
    "sentence": "The Committee continues to closely monitor inflation indicators and global economic and financial developments.",
    "source": "statement_20170503.txt",
    "doc_type": "statement",
    "date": "2017-05-03",
    "context_question": null,
    "top": "",
    "sen": "",
    "ten": "",
    "hor": "",
    "com": "",
    "ris": "",
    "wid": ""
  },
  {
    "id": "3c518f17-c03e-4aef-9f1c-e5fd4e79308f",
    "sentence": "The Committee also is prepared to purchase longer-term Treasury securities if evolving circumstances indicate that such transactions would be particularly effective in improving conditions in private credit markets.",
    "source": "statement_20090128.txt",
    "doc_type": "statement",
    "date": "2009-01-28",
    "context_question": null,
    "top": "",
    "sen": "",
    "ten": "",
    "hor": "",
    "com": "",
    "ris": "",
    "wid": ""
  },
  {
    "id": "7296d990-d193-4185-bc65-d34eb4974ff8",
    "sentence": "In addition, the Federal Reserve will continue to increase its holdings of Treasury securities by at least $80 billion per month and of agency mortgage-backed securities by at least $40 billion per month until substantial further progress has been made toward the Committee's maximum employment and price stability goals. These asset purchases help foster smooth market functioning and accommodative financial conditions, thereby supporting the flow of credit to households and businesses.",
    "source": "statement_20201216.txt",
    "doc_type": "statement",
    "date": "2020-12-16",
    "context_question": null,
    "top": "",
    "sen": "",
    "ten": "",
    "hor": "",
    "com": "",
    "ris": "",
    "wid": ""
  },
  {
    "id": "350dab9c-49a4-47cd-bac8-cb92aab386ac",
    "sentence": "In addition, the Committee will maintain its existing policy of rolling over maturing Treasury securities at auction.",
    "source": "statement_20110921.txt",
    "doc_type": "statement",
    "date": "2011-09-21",
    "context_question": null,
    "top": "",
    "sen": "",
    "ten": "",
    "hor": "",
    "com": "",
    "ris": "",
    "wid": ""
  },
  {
    "id": "9ae6a5d8-3a36-40da-a1b8-dffc98b7d30a",
    "sentence": "To support a stronger economic recovery and to help ensure that inflation, over time, is at levels consistent with the dual mandate, the Committee decided today to extend the average maturity of its holdings of securities.",
    "source": "statement_20110921.txt",
    "doc_type": "statement",
    "date": "2011-09-21",
    "context_question": null,
    "top": "",
    "sen": "",
    "ten": "",
    "hor": "",
    "com": "",
    "ris": "",
    "wid": ""
  },
  {
    "id": "7358be0c-be89-4553-b727-5fa4292c871e",
    "sentence": "In support of its goals and in light of the shift in the balance of risks, the Committee decided to lower the target range for the federal funds rate by 1/4 percentage point to 3-1/2 to 3‑3/4 percent.",
    "source": "statement_20251210.txt",
    "doc_type": "statement",
    "date": "2025-12-10",
    "context_question": null,
    "top": "",
    "sen": "",
    "ten": "",
    "hor": "",
    "com": "",
    "ris": "",
    "wid": ""
  },
  {
    "id": "3931c8d7-e2e2-4c48-9fc4-b4bcdb33bf68",
    "sentence": "When the Committee decides to begin to remove policy accommodation, it will take a balanced approach consistent with its longer-run goals of maximum employment and inflation of 2 percent.",
    "source": "statement_20140129.txt",
    "doc_type": "statement",
    "date": "2014-01-29",
    "context_question": null,
    "top": "",
    "sen": "",
    "ten": "",
    "hor": "",
    "com": "",
    "ris": "",
    "wid": ""
  },
  {
    "id": "3af7187a-4e28-453d-b9bb-d0c8c4be9f9a",
    "sentence": "The Committee also decided to continue through the end of the year its program to extend the average maturity of its holdings of securities as announced in June, and it is maintaining its existing policy of reinvesting principal payments from its holdings of agency debt and agency mortgage-backed securities in agency mortgage-backed securities.",
    "source": "statement_20120801.txt",
    "doc_type": "statement",
    "date": "2012-08-01",
    "context_question": null,
    "top": "",
    "sen": "",
    "ten": "",
    "hor": "",
    "com": "",
    "ris": "",
    "wid": ""
  },
  {
    "id": "6bcf665d-104b-410a-97ff-82d4f15de128",
    "sentence": "The ongoing public health crisis continues to weigh on economic activity, employment, and inflation, and poses considerable risks to the economic outlook.",
    "source": "statement_20210317.txt",
    "doc_type": "statement",
    "date": "2021-03-17",
    "context_question": null,
    "top": "",
    "sen": "",
    "ten": "",
    "hor": "",
    "com": "",
    "ris": "",
    "wid": ""
  },
  {
    "id": "42e4e02a-d117-4cb4-a096-3d3e448ed697",
    "sentence": "The Committee anticipates that a gradual recovery in economic activity will begin later this year, but the downside risks to that outlook are significant. In light of the declines in the prices of energy and other commodities in recent months and the prospects for considerable economic slack, the Committee expects that inflation pressures will remain subdued in coming quarters. Moreover, the Committee sees some risk that inflation could persist for a time below rates that best foster economic growth and price stability in the longer term.",
    "source": "statement_20090128.txt",
    "doc_type": "statement",
    "date": "2009-01-28",
    "context_question": null,
    "top": "",
    "sen": "",
    "ten": "",
    "hor": "",
    "com": "",
    "ris": "",
    "wid": ""
  },
  {
    "id": "c354877b-1f09-4933-8798-ca14265512d0",
    "sentence": "In light of improved functioning of financial markets, the Federal Reserve will be closing the Asset-Backed Commercial Paper Money Market Mutual Fund Liquidity Facility, the Commercial Paper Funding Facility, the Primary Dealer Credit Facility, and the Term Securities Lending Facility on February 1, as previously announced.",
    "source": "statement_20100127.txt",
    "doc_type": "statement",
    "date": "2010-01-27",
    "context_question": null,
    "top": "",
    "sen": "",
    "ten": "",
    "hor": "",
    "com": "",
    "ris": "",
    "wid": ""
  },
  {
    "id": "f831bd97-f73a-4019-9252-5953dfd13116",
    "sentence": "Auctions will be held on a weekly basis, beginning on March 27, 2008.",
    "source": "statement_20080311.txt",
    "doc_type": "statement",
    "date": "2008-03-11",
    "context_question": null,
    "top": "",
    "sen": "",
    "ten": "",
    "hor": "",
    "com": "",
    "ris": "",
    "wid": ""
  },
  {
    "id": "4914bdfb-0dcf-4b75-84ad-f1b4bcf633f0",
    "sentence": "In response to the reemergence of strains in U.S. dollar short-term funding markets in Europe, the Bank of Canada, the Bank of England, the European Central Bank, the Federal Reserve, and the Swiss National Bank are announcing the reestablishment of temporary U.S. dollar liquidity swap facilities. These facilities are designed to help improve liquidity conditions in U.S. dollar funding markets and to prevent the spread of strains to other markets and financial centers.",
    "source": "statement_20100509.txt",
    "doc_type": "statement",
    "date": "2010-05-09",
    "context_question": null,
    "top": "",
    "sen": "",
    "ten": "",
    "hor": "",
    "com": "",
    "ris": "",
    "wid": ""
  },
  {
    "id": "941b3702-ea76-41c3-80d4-bda7aa5d2a5f",
    "sentence": "Uncertainty around the economic outlook has increased.",
    "source": "statement_20250319.txt",
    "doc_type": "statement",
    "date": "2025-03-19",
    "context_question": null,
    "top": "",
    "sen": "",
    "ten": "",
    "hor": "",
    "com": "",
    "ris": "",
    "wid": ""
  },
  {
    "id": "c1667db9-df62-485f-96f9-f6ac5ceeae00",
    "sentence": "In determining the size, pace, and composition of its asset purchases, the Committee will, as always, take appropriate account of the likely efficacy and costs of such purchases.",
    "source": "statement_20130130.txt",
    "doc_type": "statement",
    "date": "2013-01-30",
    "context_question": null,
    "top": "",
    "sen": "",
    "ten": "",
    "hor": "",
    "com": "",
    "ris": "",
    "wid": ""
  },
  {
    "id": "3af6e38f-c7bc-42a0-bdf2-58b182cdbabf",
    "sentence": "The Committee sees the risks to the outlook for the economy and the labor market as having become more nearly balanced. The Committee recognizes that inflation persistently below its 2 percent objective could pose risks to economic performance, and it is monitoring inflation developments carefully for evidence that inflation will move back toward its objective over the medium term.",
    "source": "statement_20140129.txt",
    "doc_type": "statement",
    "date": "2014-01-29",
    "context_question": null,
    "top": "",
    "sen": "",
    "ten": "",
    "hor": "",
    "com": "",
    "ris": "",
    "wid": ""
  },
  {
    "id": "21d70f54-b02d-484c-9391-fffa9c421f4b",
    "sentence": "Federal Reserve Actions The Federal Reserve announced today an expansion of its securities lending program. Under this new Term Securities Lending Facility (TSLF), the Federal Reserve will lend up to $200 billion of Treasury securities to primary dealers secured for a term of 28 days (rather than overnight, as in the existing program) by a pledge of other securities, including federal agency debt, federal agency residential-mortgage-backed securities (MBS), and non-agency AAA/Aaa-rated private-label residential MBS.",
    "source": "statement_20080311.txt",
    "doc_type": "statement",
    "date": "2008-03-11",
    "context_question": null,
    "top": "",
    "sen": "",
    "ten": "",
    "hor": "",
    "com": "",
    "ris": "",
    "wid": ""
  },
  {
    "id": "12a34d3c-d430-4987-ab8d-7a3ec3b3f67f",
    "sentence": "Taking into account the extent of federal fiscal retrenchment, the Committee sees the improvement in economic activity and labor market conditions since it began its asset purchase program a year ago as consistent with growing underlying strength in the broader economy. However, the Committee decided to await more evidence that progress will be sustained before adjusting the pace of its purchases.",
    "source": "statement_20130918.txt",
    "doc_type": "statement",
    "date": "2013-09-18",
    "context_question": null,
    "top": "",
    "sen": "",
    "ten": "",
    "hor": "",
    "com": "",
    "ris": "",
    "wid": ""
  },
  {
    "id": "58533cb2-435f-4e94-8896-15a08592bac9",
    "sentence": "In a related action, the Board of Governors unanimously approved a 25-basis-point decrease in the discount rate to 2-1/4 percent. In taking this action, the Board approved the requests submitted by the Boards of Directors of the Federal Reserve Banks of New York, Cleveland, Atlanta, and San Francisco.",
    "source": "statement_20080430.txt",
    "doc_type": "statement",
    "date": "2008-04-30",
    "context_question": null,
    "top": "",
    "sen": "",
    "ten": "",
    "hor": "",
    "com": "",
    "ris": "",
    "wid": ""
  },
  {
    "id": "3cfaf5c5-fd77-48d4-95d5-cadc007d35a6",
    "sentence": "In view of realized and expected labor market conditions and inflation, the Committee decided to maintain the target range for the federal funds rate at 2 to 2-1/4 percent.",
    "source": "statement_20181108.txt",
    "doc_type": "statement",
    "date": "2018-11-08",
    "context_question": null,
    "top": "",
    "sen": "",
    "ten": "",
    "hor": "",
    "com": "",
    "ris": "",
    "wid": ""
  },
  {
    "id": "7b5e0106-4990-4404-847a-e53e777b3535",
    "sentence": "Risks to the economic outlook remain, including from new variants of the virus.",
    "source": "statement_20220126.txt",
    "doc_type": "statement",
    "date": "2022-01-26",
    "context_question": null,
    "top": "",
    "sen": "",
    "ten": "",
    "hor": "",
    "com": "",
    "ris": "",
    "wid": ""
  },
  {
    "id": "eb304249-e797-4c8e-acbf-d9d31fc1b350",
    "sentence": "The Committee will continue to carefully monitor the size and composition of the Federal Reserve's balance sheet in light of financial and economic developments.",
    "source": "statement_20090429.txt",
    "doc_type": "statement",
    "date": "2009-04-29",
    "context_question": null,
    "top": "",
    "sen": "",
    "ten": "",
    "hor": "",
    "com": "",
    "ris": "",
    "wid": ""
  },
  {
    "id": "31635dca-ff68-45f3-b7a7-8e692c7e9793",
    "sentence": "Uncertainty about the economic outlook remains elevated. The Committee is attentive to the risks to both sides of its dual mandate and judges that downside risks to employment rose in recent months.",
    "source": "statement_20251210.txt",
    "doc_type": "statement",
    "date": "2025-12-10",
    "context_question": null,
    "top": "",
    "sen": "",
    "ten": "",
    "hor": "",
    "com": "",
    "ris": "",
    "wid": ""
  },
  {
    "id": "965f63a1-dc90-48e1-8dd4-e65690fa772c",
    "sentence": "The Committee expects inflation to moderate in coming quarters, reflecting a projected leveling-out of energy and other commodity prices and an easing of pressures on resource utilization.",
    "source": "statement_20080318.txt",
    "doc_type": "statement",
    "date": "2008-03-18",
    "context_question": null,
    "top": "",
    "sen": "",
    "ten": "",
    "hor": "",
    "com": "",
    "ris": "",
    "wid": ""
  },
  {
    "id": "1cf61e2f-6fd7-4bd2-9a4f-7fa3981640a6",
    "sentence": "Inflation is anticipated to remain near its recent low level in the near term but the Committee expects inflation to rise gradually toward 2 percent over the medium term as the labor market improves further and the transitory effects of declines in energy and import prices dissipate.",
    "source": "statement_20151028.txt",
    "doc_type": "statement",
    "date": "2015-10-28",
    "context_question": null,
    "top": "",
    "sen": "",
    "ten": "",
    "hor": "",
    "com": "",
    "ris": "",
    "wid": ""
  },
  {
    "id": "a830afe7-84b7-4911-9892-6cc980c98455",
    "sentence": "The Committee sees the downside risks to the outlook for the economy and the labor market as having diminished, on net, since last fall, but the tightening of financial conditions observed in recent months, if sustained, could slow the pace of improvement in the economy and labor market. The Committee recognizes that inflation persistently below its 2 percent objective could pose risks to economic performance, but it anticipates that inflation will move back toward its objective over the medium term.",
    "source": "statement_20130918.txt",
    "doc_type": "statement",
    "date": "2013-09-18",
    "context_question": null,
    "top": "",
    "sen": "",
    "ten": "",
    "hor": "",
    "com": "",
    "ris": "",
    "wid": ""
  },
  {
    "id": "b7ffd95a-6765-436f-a850-27c156078ae7",
    "sentence": "The actions announced today supplement the measures announced by the Federal Reserve on Friday to boost the size of the Term Auction Facility to $100 billion and to undertake a series of term repurchase transactions that will cumulate to $100 billion. Information on Related Actions Being Taken by Other Central Banks Information on the actions that will be taken by other central banks is available at the following websites: Bank of Canada Bank of England European Central Bank Swiss National Bank (61 KB PDF) Statements by Other Central Banks Bank of Japan Sveriges Riksbank Term Securities Lending Facility Terms and conditions Frequently asked questions Federal Reserve Actions The Federal Reserve announced today an expansion of its securities lending program.",
    "source": "statement_20080311.txt",
    "doc_type": "statement",
    "date": "2008-03-11",
    "context_question": null,
    "top": "",
    "sen": "",
    "ten": "",
    "hor": "",
    "com": "",
    "ris": "",
    "wid": ""
  },
  {
    "id": "7950f7e8-993c-437f-8fe7-b88ec65faa63",
    "sentence": "Furthermore, strains in global financial markets continue to pose significant downside risks to the economic outlook. The Committee also anticipates that inflation over the medium term likely will run at or below its 2 percent objective.",
    "source": "statement_20121212.txt",
    "doc_type": "statement",
    "date": "2012-12-12",
    "context_question": null,
    "top": "",
    "sen": "",
    "ten": "",
    "hor": "",
    "com": "",
    "ris": "",
    "wid": ""
  },
  {
    "id": "e25ff2d2-c10d-4d35-9bbf-5f74afb6ccb9",
    "sentence": "What is the Federal Reserve's maturity extension program (referred to by some as \"operation twist\") and what is its purpose?",
    "source": "statement_20110921.txt",
    "doc_type": "statement",
    "date": "2011-09-21",
    "context_question": null,
    "top": "",
    "sen": "",
    "ten": "",
    "hor": "",
    "com": "",
    "ris": "",
    "wid": ""
  },
  {
    "id": "4476e423-6ae1-4cfc-89e0-d2e4ee78a744",
    "sentence": "developments of recent months.",
    "source": "statement_20160316.txt",
    "doc_type": "statement",
    "date": "2016-03-16",
    "context_question": null,
    "top": "",
    "sen": "",
    "ten": "",
    "hor": "",
    "com": "",
    "ris": "",
    "wid": ""
  },
  {
    "id": "f6935fdf-d4d3-4bdb-95d3-2f9a33ae7dde",
    "sentence": "Inflation on a 12‑month basis is expected to remain somewhat below 2 percent in the near term but to stabilize around the Committee's 2 percent objective over the medium term.",
    "source": "statement_20171213.txt",
    "doc_type": "statement",
    "date": "2017-12-13",
    "context_question": null,
    "top": "",
    "sen": "",
    "ten": "",
    "hor": "",
    "com": "",
    "ris": "",
    "wid": ""
  },
  {
    "id": "dc797525-3c54-46ff-8170-acced439d0ba",
    "sentence": "The Federal Reserve is in the process of winding down its Term Auction Facility: $50 billion in 28-day credit will be offered on February 8 and $25 billion in 28-day credit will be offered at the final auction on March 8.",
    "source": "statement_20100127.txt",
    "doc_type": "statement",
    "date": "2010-01-27",
    "context_question": null,
    "top": "",
    "sen": "",
    "ten": "",
    "hor": "",
    "com": "",
    "ris": "",
    "wid": ""
  },
  {
    "id": "ef4dac2f-9df7-41f0-aa61-c9f974d65b66",
    "sentence": "The Committee will continue to monitor the economic outlook and financial developments and will employ its policy tools as necessary to support the economic recovery and to help ensure that inflation, over time, is at levels consistent with its mandate. In light of the improving economy, Mr. Hoenig was concerned that a continued high level of monetary accommodation would increase the risks of future economic and financial imbalances and, over time, would cause an increase in long-term inflation expectations that could destabilize the economy.",
    "source": "statement_20101214.txt",
    "doc_type": "statement",
    "date": "2010-12-14",
    "context_question": null,
    "top": "",
    "sen": "",
    "ten": "",
    "hor": "",
    "com": "",
    "ris": "",
    "wid": ""
  },
  {
    "id": "3a3c0e2e-4ccf-4a08-be08-a020ec37f3da",
    "sentence": "Under this new Term Securities Lending Facility (TSLF), the Federal Reserve will lend up to $200 billion of Treasury securities to primary dealers secured for a term of 28 days (rather than overnight, as in the existing program) by a pledge of other securities, including federal agency debt, federal agency residential-mortgage-backed securities (MBS), and non-agency AAA/Aaa-rated private-label residential MBS.",
    "source": "statement_20080311.txt",
    "doc_type": "statement",
    "date": "2008-03-11",
    "context_question": null,
    "top": "",
    "sen": "",
    "ten": "",
    "hor": "",
    "com": "",
    "ris": "",
    "wid": ""
  },
  {
    "id": "e00742dc-226c-4df7-b4b6-c23985dc142d",
    "sentence": "Near-term risks to the economic outlook appear roughly balanced, but the Committee is monitoring inflation developments closely.",
    "source": "statement_20180321.txt",
    "doc_type": "statement",
    "date": "2018-03-21",
    "context_question": null,
    "top": "",
    "sen": "",
    "ten": "",
    "hor": "",
    "com": "",
    "ris": "",
    "wid": ""
  },
  {
    "id": "819e56a5-5909-4ccd-bdb4-f66684bc484c",
    "sentence": "Based on its current assessment, the Committee judges that it can be patient in beginning to normalize the stance of monetary policy. The Committee sees this guidance as consistent with its previous statement that it likely will be appropriate to maintain the 0 to 1/4 percent target range for the federal funds rate for a considerable time following the end of its asset purchase program in October, especially if projected inflation continues to run below the Committee's 2 percent longer-run goal, and provided that longer-term inflation expectations remain well anchored.",
    "source": "statement_20141217.txt",
    "doc_type": "statement",
    "date": "2014-12-17",
    "context_question": null,
    "top": "",
    "sen": "",
    "ten": "",
    "hor": "",
    "com": "",
    "ris": "",
    "wid": ""
  },
  {
    "id": "3d633df0-2e9d-4321-945e-d327fb36f3fd",
    "sentence": "Inflation is anticipated to remain near its recent low level in the near term, but the Committee expects inflation to rise gradually toward 2 percent over the medium term as the labor market improves further and the transitory effects of earlier declines in energy and import prices dissipate.",
    "source": "statement_20150729.txt",
    "doc_type": "statement",
    "date": "2015-07-29",
    "context_question": null,
    "top": "",
    "sen": "",
    "ten": "",
    "hor": "",
    "com": "",
    "ris": "",
    "wid": ""
  },
  {
    "id": "17180895-d596-41ea-a2b4-e5f4be4f89b7",
    "sentence": "The Federal Reserve will also be working with its central bank counterparties to close its temporary liquidity swap arrangements by February 1. The Federal Reserve expects that amounts provided under the Term Auction Facility will continue to be scaled back in early 2010.",
    "source": "statement_20091216.txt",
    "doc_type": "statement",
    "date": "2009-12-16",
    "context_question": null,
    "top": "",
    "sen": "",
    "ten": "",
    "hor": "",
    "com": "",
    "ris": "",
    "wid": ""
  },
  {
    "id": "c7c388c1-ad2e-48ce-8b36-225d81a4bf9d",
    "sentence": "The economic outlook has strengthened in recent months. The Committee expects that, with further gradual adjustments in the stance of monetary policy, economic activity will expand at a moderate pace in the medium term and labor market conditions will remain strong.",
    "source": "statement_20180321.txt",
    "doc_type": "statement",
    "date": "2018-03-21",
    "context_question": null,
    "top": "",
    "sen": "",
    "ten": "",
    "hor": "",
    "com": "",
    "ris": "",
    "wid": ""
  },
  {
    "id": "1b879b7b-42b8-40d8-b48a-30be4da1cc87",
    "sentence": "Frequently Asked Questions",
    "source": "statement_20120620.txt",
    "doc_type": "statement",
    "date": "2012-06-20",
    "context_question": null,
    "top": "",
    "sen": "",
    "ten": "",
    "hor": "",
    "com": "",
    "ris": "",
    "wid": ""
  },
  {
    "id": "8482cf57-2452-4e3c-a0e0-eea6f59ec9dd",
    "sentence": "In current circumstances, depository institutions may experience unusual funding needs because of dislocations in money and credit markets.",
    "source": "statement_20070810.txt",
    "doc_type": "statement",
    "date": "2007-08-10",
    "context_question": null,
    "top": "",
    "sen": "",
    "ten": "",
    "hor": "",
    "com": "",
    "ris": "",
    "wid": ""
  },
  {
    "id": "2d647fe1-8b92-4c11-9930-0571f7f5c34b",
    "sentence": "It will be necessary to continue to monitor inflation developments carefully.",
    "source": "statement_20080430.txt",
    "doc_type": "statement",
    "date": "2008-04-30",
    "context_question": null,
    "top": "",
    "sen": "",
    "ten": "",
    "hor": "",
    "com": "",
    "ris": "",
    "wid": ""
  },
  {
    "id": "883e498a-fdd4-4135-84d4-81a95dd38bce",
    "sentence": "Uncertainty about the economic outlook remains elevated.",
    "source": "statement_20250730.txt",
    "doc_type": "statement",
    "date": "2025-07-30",
    "context_question": null,
    "top": "",
    "sen": "",
    "ten": "",
    "hor": "",
    "com": "",
    "ris": "",
    "wid": ""
  },
  {
    "id": "f375819d-8d44-4d15-a21f-1ff287433213",
    "sentence": "In light of the current shortfall of inflation from 2 percent, the Committee will carefully monitor actual and expected progress toward its inflation goal. The Committee expects that economic conditions will evolve in a manner that will warrant only gradual increases in the federal funds rate; the federal funds rate is likely to remain, for some time, below levels that are expected to prevail in the longer run.",
    "source": "statement_20170201.txt",
    "doc_type": "statement",
    "date": "2017-02-01",
    "context_question": null,
    "top": "",
    "sen": "",
    "ten": "",
    "hor": "",
    "com": "",
    "ris": "",
    "wid": ""
  },
  {
    "id": "1e022562-3983-4d55-a2d2-bcb6a35ffecf",
    "sentence": "The Committee is maintaining its existing policy of reinvesting principal payments from its holdings of agency debt and agency mortgage-backed securities in agency mortgage-backed securities and of rolling over maturing Treasury securities at auction. This policy, by keeping the Committee’s holdings of longer-term securities at sizable levels, should help maintain accommodative financial conditions.",
    "source": "statement_20150128.txt",
    "doc_type": "statement",
    "date": "2015-01-28",
    "context_question": null,
    "top": "",
    "sen": "",
    "ten": "",
    "hor": "",
    "com": "",
    "ris": "",
    "wid": ""
  },
  {
    "id": "31f3b563-0497-4e93-8b5d-19d2502acf7c",
    "sentence": "The economic outlook is uncertain, and the Committee remains highly attentive to inflation risks.",
    "source": "statement_20240612.txt",
    "doc_type": "statement",
    "date": "2024-06-12",
    "context_question": null,
    "top": "",
    "sen": "",
    "ten": "",
    "hor": "",
    "com": "",
    "ris": "",
    "wid": ""
  },
  {
    "id": "a22fe015-56d2-4bf9-8265-2266d1f14924",
    "sentence": "The Committee will closely monitor incoming information on economic and financial developments in coming months and will continue its purchases of Treasury and agency mortgage-backed securities, and employ its other policy tools as appropriate, until the outlook for the labor market has improved substantially in a context of price stability.",
    "source": "statement_20140917.txt",
    "doc_type": "statement",
    "date": "2014-09-17",
    "context_question": null,
    "top": "",
    "sen": "",
    "ten": "",
    "hor": "",
    "com": "",
    "ris": "",
    "wid": ""
  },
  {
    "id": "da607f89-f4cb-4fe3-8db5-b3e0976f0659",
    "sentence": "The Committee will carefully monitor actual and expected inflation developments relative to its symmetric inflation goal. The Committee expects that economic conditions will evolve in a manner that will warrant gradual increases in the federal funds rate; the federal funds rate is likely to remain, for some time, below levels that are expected to prevail in the longer run.",
    "source": "statement_20171213.txt",
    "doc_type": "statement",
    "date": "2017-12-13",
    "context_question": null,
    "top": "",
    "sen": "",
    "ten": "",
    "hor": "",
    "com": "",
    "ris": "",
    "wid": ""
  },
  {
    "id": "d84c23b3-6d8a-48ae-938d-0fdba8fbbef3",
    "sentence": "The Federal Reserve is providing liquidity to facilitate the orderly functioning of financial markets.",
    "source": "statement_20070810.txt",
    "doc_type": "statement",
    "date": "2007-08-10",
    "context_question": null,
    "top": "",
    "sen": "",
    "ten": "",
    "hor": "",
    "com": "",
    "ris": "",
    "wid": ""
  },
  {
    "id": "123ce34a-e031-482d-8b85-b2e50968773d",
    "sentence": "The Committee will continue to assess the effects of financial and other developments on economic prospects and will act in a timely manner as needed to address those risks.",
    "source": "statement_20080130.txt",
    "doc_type": "statement",
    "date": "2008-01-30",
    "context_question": null,
    "top": "",
    "sen": "",
    "ten": "",
    "hor": "",
    "com": "",
    "ris": "",
    "wid": ""
  },
  {
    "id": "06be4333-a491-403f-b730-331d441706be",
    "sentence": "Beginning in May, the Committee will add to its holdings of agency mortgage-backed securities at a pace of $20 billion per month rather than $25 billion per month, and will add to its holdings of longer-term Treasury securities at a pace of $25 billion per month rather than $30 billion per month.",
    "source": "statement_20140430.txt",
    "doc_type": "statement",
    "date": "2014-04-30",
    "context_question": null,
    "top": "",
    "sen": "",
    "ten": "",
    "hor": "",
    "com": "",
    "ris": "",
    "wid": ""
  },
  {
    "id": "5c476bdc-c948-43f9-94f1-190bd8b7d31b",
    "sentence": "The Committee seeks to achieve maximum employment and inflation at the rate of 2 percent over the longer run. In support of these goals, the Committee decided to keep the target range for the federal funds rate at 0 to 1/4 percent.",
    "source": "statement_20220126.txt",
    "doc_type": "statement",
    "date": "2022-01-26",
    "context_question": null,
    "top": "",
    "sen": "",
    "ten": "",
    "hor": "",
    "com": "",
    "ris": "",
    "wid": ""
  },
  {
    "id": "79c4eca7-edcb-4b11-9301-3b65522db241",
    "sentence": "In view of realized and expected labor market conditions and inflation, the Committee decided to raise the target range for the federal funds rate to 1 to 1-1/4 percent.",
    "source": "statement_20170614.txt",
    "doc_type": "statement",
    "date": "2017-06-14",
    "context_question": null,
    "top": "",
    "sen": "",
    "ten": "",
    "hor": "",
    "com": "",
    "ris": "",
    "wid": ""
  },
  {
    "id": "af4b9974-66e1-4621-ad56-c6ff51ac01e2",
    "sentence": "The Committee will continue to carefully monitor the size and composition of the Federal Reserve's balance sheet in light of evolving financial and economic developments.",
    "source": "statement_20090318.txt",
    "doc_type": "statement",
    "date": "2009-03-18",
    "context_question": null,
    "top": "",
    "sen": "",
    "ten": "",
    "hor": "",
    "com": "",
    "ris": "",
    "wid": ""
  },
  {
    "id": "b4b5d85a-6111-48b8-8628-b271285902c8",
    "sentence": "The Committee is maintaining its existing policy of reinvesting principal payments from its holdings of agency debt and agency mortgage-backed securities in agency mortgage-backed securities and of rolling over maturing Treasury securities at auction, and it anticipates doing so until normalization of the level of the federal funds rate is well under way. This policy, by keeping the Committee's holdings of longer-term securities at sizable levels, should help maintain accommodative financial conditions.",
    "source": "statement_20170503.txt",
    "doc_type": "statement",
    "date": "2017-05-03",
    "context_question": null,
    "top": "",
    "sen": "",
    "ten": "",
    "hor": "",
    "com": "",
    "ris": "",
    "wid": ""
  },
  {
    "id": "d31aed3f-d6f3-4e2e-a7f4-f412cf6e82f1",
    "sentence": "The Committee will conclude the reduction of its aggregate securities holdings in the System Open Market Account in August, two months earlier than previously indicated.",
    "source": "statement_20190731.txt",
    "doc_type": "statement",
    "date": "2019-07-31",
    "context_question": null,
    "top": "",
    "sen": "",
    "ten": "",
    "hor": "",
    "com": "",
    "ris": "",
    "wid": ""
  },
  {
    "id": "a55d9ae5-6441-4684-af7b-284892d1b400",
    "sentence": "However, the Committee will continue to pay close attention to the evolution of inflation and inflation expectations.",
    "source": "statement_20111213.txt",
    "doc_type": "statement",
    "date": "2011-12-13",
    "context_question": null,
    "top": "",
    "sen": "",
    "ten": "",
    "hor": "",
    "com": "",
    "ris": "",
    "wid": ""
  },
  {
    "id": "8b5d32fa-0d6f-4f39-a1c5-a16b138fbdd8",
    "sentence": "Nonetheless, the Committee anticipates a gradual return to higher levels of resource utilization in a context of price stability, although the pace of economic recovery is likely to be moderate for a time.",
    "source": "statement_20100623.txt",
    "doc_type": "statement",
    "date": "2010-06-23",
    "context_question": null,
    "top": "",
    "sen": "",
    "ten": "",
    "hor": "",
    "com": "",
    "ris": "",
    "wid": ""
  },
  {
    "id": "956d18c4-1fe8-467a-ba30-9e3f904e02a4",
    "sentence": "The Committee anticipates that it will be appropriate to raise the target range for the federal funds rate when it has seen some further improvement in the labor market and is reasonably confident that inflation will move back to its 2 percent objective over the medium term.",
    "source": "statement_20150917.txt",
    "doc_type": "statement",
    "date": "2015-09-17",
    "context_question": null,
    "top": "",
    "sen": "",
    "ten": "",
    "hor": "",
    "com": "",
    "ris": "",
    "wid": ""
  },
  {
    "id": "882a9da2-5d98-4b7d-ba2a-4cadfff5d9b9",
    "sentence": "In addition, the Federal Reserve will continue to increase its holdings of Treasury securities by at least $80 billion per month and of agency mortgage‑backed securities by at least $40 billion per month until substantial further progress has been made toward the Committee's maximum employment and price stability goals. These asset purchases help foster smooth market functioning and accommodative financial conditions, thereby supporting the flow of credit to households and businesses.",
    "source": "statement_20210616.txt",
    "doc_type": "statement",
    "date": "2021-06-16",
    "context_question": null,
    "top": "",
    "sen": "",
    "ten": "",
    "hor": "",
    "com": "",
    "ris": "",
    "wid": ""
  },
  {
    "id": "36b776b5-71d9-4542-b9ed-00195ccdfc05",
    "sentence": "The Committee discussed the range of policy tools available to promote a stronger economic recovery in a context of price stability.",
    "source": "statement_20110921.txt",
    "doc_type": "statement",
    "date": "2011-09-21",
    "context_question": null,
    "top": "",
    "sen": "",
    "ten": "",
    "hor": "",
    "com": "",
    "ris": "",
    "wid": ""
  },
  {
    "id": "6bbe1aed-f64f-4da2-94f2-5d6393a1dfde",
    "sentence": "The Committee would be prepared to adjust the stance of monetary policy as appropriate if risks emerge that could impede the attainment of the Committee’s goals.",
    "source": "statement_20220504.txt",
    "doc_type": "statement",
    "date": "2022-05-04",
    "context_question": null,
    "top": "",
    "sen": "",
    "ten": "",
    "hor": "",
    "com": "",
    "ris": "",
    "wid": ""
  },
  {
    "id": "4edc86bf-87a3-4a31-953f-3ddd58789c1f",
    "sentence": "Taking into account the extent of federal fiscal retrenchment over the past year, the Committee sees the improvement in economic activity and labor market conditions since it began its asset purchase program as consistent with growing underlying strength in the broader economy. However, the Committee decided to await more evidence that progress will be sustained before adjusting the pace of its purchases.",
    "source": "statement_20131030.txt",
    "doc_type": "statement",
    "date": "2013-10-30",
    "context_question": null,
    "top": "",
    "sen": "",
    "ten": "",
    "hor": "",
    "com": "",
    "ris": "",
    "wid": ""
  },
  {
    "id": "b7d1bd12-d6e9-45bf-b597-5b90291470cc",
    "sentence": "The stance of monetary policy remains accommodative after this increase, thereby supporting further improvement in labor market conditions and a return to 2 percent inflation.",
    "source": "statement_20151216.txt",
    "doc_type": "statement",
    "date": "2015-12-16",
    "context_question": null,
    "top": "",
    "sen": "",
    "ten": "",
    "hor": "",
    "com": "",
    "ris": "",
    "wid": ""
  },
  {
    "id": "5f5f503f-c04b-4baa-86d8-2d661229ee09",
    "sentence": "Beginning in June, the Committee will slow the pace of decline of its securities holdings by reducing the monthly redemption cap on Treasury securities from $60 billion to $25 billion. The Committee will maintain the monthly redemption cap on agency debt and agency mortgage‑backed securities at $35 billion and will reinvest any principal payments in excess of this cap into Treasury securities.",
    "source": "statement_20240501.txt",
    "doc_type": "statement",
    "date": "2024-05-01",
    "context_question": null,
    "top": "",
    "sen": "",
    "ten": "",
    "hor": "",
    "com": "",
    "ris": "",
    "wid": ""
  },
  {
    "id": "110a16f0-9ae7-426a-8740-47fde8904f78",
    "sentence": "Consistent with its statutory mandate, the Committee seeks to foster maximum employment and price stability. The Committee currently expects that, with gradual adjustments in the stance of monetary policy, economic activity will expand at a moderate pace and labor market indicators will continue to strengthen.",
    "source": "statement_20160316.txt",
    "doc_type": "statement",
    "date": "2016-03-16",
    "context_question": null,
    "top": "",
    "sen": "",
    "ten": "",
    "hor": "",
    "com": "",
    "ris": "",
    "wid": ""
  },
  {
    "id": "179120a2-2967-4432-811a-c8b0c41a01fc",
    "sentence": "The balance sheet normalization program initiated in October 2017 is proceeding.",
    "source": "statement_20171101.txt",
    "doc_type": "statement",
    "date": "2017-11-01",
    "context_question": null,
    "top": "",
    "sen": "",
    "ten": "",
    "hor": "",
    "com": "",
    "ris": "",
    "wid": ""
  },
  {
    "id": "b684f9d0-c1c0-44ee-9675-d14575fdee1b",
    "sentence": "The Committee will continue to evaluate its purchases of securities in light of the evolving economic outlook and conditions in financial markets.",
    "source": "statement_20100127.txt",
    "doc_type": "statement",
    "date": "2010-01-27",
    "context_question": null,
    "top": "",
    "sen": "",
    "ten": "",
    "hor": "",
    "com": "",
    "ris": "",
    "wid": ""
  },
  {
    "id": "ba80ecd0-a20d-4ff9-aae3-2ea8f99803cb",
    "sentence": "However, the actual path of the federal funds rate will depend on the economic outlook as informed by incoming data.",
    "source": "statement_20180502.txt",
    "doc_type": "statement",
    "date": "2018-05-02",
    "context_question": null,
    "top": "",
    "sen": "",
    "ten": "",
    "hor": "",
    "com": "",
    "ris": "",
    "wid": ""
  },
  {
    "id": "86d6d7e1-5e64-45c0-9c7c-9ff45308e8c0",
    "sentence": "The Committee also will maintain its existing policy of reinvesting principal payments from its securities holdings. The Committee will regularly review the size and composition of its securities holdings and is prepared to adjust those holdings as appropriate.",
    "source": "statement_20110809.txt",
    "doc_type": "statement",
    "date": "2011-08-09",
    "context_question": null,
    "top": "",
    "sen": "",
    "ten": "",
    "hor": "",
    "com": "",
    "ris": "",
    "wid": ""
  },
  {
    "id": "62937ec7-d753-45c3-b2fb-4a09de2ec9c4",
    "sentence": "The Committee expects inflation to moderate in coming quarters, but it will be necessary to continue to monitor inflation developments carefully. Today’s policy action, combined with those taken earlier, should help to promote moderate growth over time and to mitigate the risks to economic activity.",
    "source": "statement_20080130.txt",
    "doc_type": "statement",
    "date": "2008-01-30",
    "context_question": null,
    "top": "",
    "sen": "",
    "ten": "",
    "hor": "",
    "com": "",
    "ris": "",
    "wid": ""
  },
  {
    "id": "79ecf67b-d7e8-4543-9b13-d084fc308f28",
    "sentence": "As previously announced, to provide support to mortgage lending and housing markets and to improve overall conditions in private credit markets, the Federal Reserve will purchase a total of up to $1.25 trillion of agency mortgage-backed securities and up to $200 billion of agency debt by the end of the year.",
    "source": "statement_20090429.txt",
    "doc_type": "statement",
    "date": "2009-04-29",
    "context_question": null,
    "top": "",
    "sen": "",
    "ten": "",
    "hor": "",
    "com": "",
    "ris": "",
    "wid": ""
  },
  {
    "id": "7d9111d6-1efc-4325-a6de-f77f05b4eb24",
    "sentence": "The Committee also will purchase longer-term Treasury securities after its program to extend the average maturity of its holdings of Treasury securities is completed at the end of the year, initially at a pace of $45 billion per month.",
    "source": "statement_20121212.txt",
    "doc_type": "statement",
    "date": "2012-12-12",
    "context_question": null,
    "top": "",
    "sen": "",
    "ten": "",
    "hor": "",
    "com": "",
    "ris": "",
    "wid": ""
  },
  {
    "id": "62b5b0d5-fcb3-4019-b8fe-b07a80558900",
    "sentence": "However, the Committee judges that some inflation risks remain, and it will continue to monitor inflation developments carefully.",
    "source": "statement_20070918.txt",
    "doc_type": "statement",
    "date": "2007-09-18",
    "context_question": null,
    "top": "",
    "sen": "",
    "ten": "",
    "hor": "",
    "com": "",
    "ris": "",
    "wid": ""
  },
  {
    "id": "d84f5d75-0c32-4040-afd9-3f4e47d65d71",
    "sentence": "In a related action, the Board of Governors unanimously approved a 50-basis-point decrease in the discount rate to 3-1/2 percent. In taking this action, the Board approved the requests submitted by the Boards of Directors of the Federal Reserve Banks of Boston, New York, Philadelphia, Cleveland, Atlanta, Chicago, St. Louis, Kansas City, and San Francisco.",
    "source": "statement_20080130.txt",
    "doc_type": "statement",
    "date": "2008-01-30",
    "context_question": null,
    "top": "",
    "sen": "",
    "ten": "",
    "hor": "",
    "com": "",
    "ris": "",
    "wid": ""
  },
  {
    "id": "5bfc4536-d71e-4058-adc0-95d20edad0e2",
    "sentence": "The Committee also decided to continue through the end of the year its program to extend the average maturity of its holdings of securities.",
    "source": "statement_20120620.txt",
    "doc_type": "statement",
    "date": "2012-06-20",
    "context_question": null,
    "top": "",
    "sen": "",
    "ten": "",
    "hor": "",
    "com": "",
    "ris": "",
    "wid": ""
  },
  {
    "id": "66682bec-f65f-492f-99b0-4225f1cec93c",
    "sentence": "Plans for Reducing the Size of the Federal Reserve's Balance Sheet",
    "source": "statement_20220504.txt",
    "doc_type": "statement",
    "date": "2022-05-04",
    "context_question": null,
    "top": "",
    "sen": "",
    "ten": "",
    "hor": "",
    "com": "",
    "ris": "",
    "wid": ""
  },
  {
    "id": "f8d434f7-d4bf-4601-adfe-252a12c7145a",
    "sentence": "Beginning in January, the Committee will increase its holdings of Treasury securities by at least $40 billion per month and of agency mortgage‑backed securities by at least $20 billion per month. The Committee judges that similar reductions in the pace of net asset purchases will likely be appropriate each month, but it is prepared to adjust the pace of purchases if warranted by changes in the economic outlook.",
    "source": "statement_20211215.txt",
    "doc_type": "statement",
    "date": "2021-12-15",
    "context_question": null,
    "top": "",
    "sen": "",
    "ten": "",
    "hor": "",
    "com": "",
    "ris": "",
    "wid": ""
  },
  {
    "id": "9d5f9bfb-57cc-4c17-a5ea-3db1c3eb9f4a",
    "sentence": "The Committee also decided to continue its program to extend the average maturity of its holdings of securities as announced in September.",
    "source": "statement_20120425.txt",
    "doc_type": "statement",
    "date": "2012-04-25",
    "context_question": null,
    "top": "",
    "sen": "",
    "ten": "",
    "hor": "",
    "com": "",
    "ris": "",
    "wid": ""
  },
  {
    "id": "59eff94f-0388-484f-a50e-83213509fbc5",
    "sentence": "President Fisher believed that the continued strengthening of the real economy, improved outlook for labor utilization and for general price stability, and continued signs of financial market excess, will likely warrant an earlier reduction in monetary accommodation than is suggested by the Committee's stated forward guidance. President Plosser objected to the guidance indicating that it likely will be appropriate to maintain the current target range for the federal funds rate for \"a considerable time after the asset purchase program ends,\" because such language is time dependent and does not reflect the considerable economic progress that has been made toward the Committee's goals.",
    "source": "statement_20140917.txt",
    "doc_type": "statement",
    "date": "2014-09-17",
    "context_question": null,
    "top": "",
    "sen": "",
    "ten": "",
    "hor": "",
    "com": "",
    "ris": "",
    "wid": ""
  },
  {
    "id": "9b8b0c6d-d666-4aac-8650-ef6b5c095569",
    "sentence": "In support of its goals, the Committee decided to lower the target range for the federal funds rate by 1/4 percentage point to 4-1/2 to 4-3/4 percent.",
    "source": "statement_20241107.txt",
    "doc_type": "statement",
    "date": "2024-11-07",
    "context_question": null,
    "top": "",
    "sen": "",
    "ten": "",
    "hor": "",
    "com": "",
    "ris": "",
    "wid": ""
  },
  {
    "id": "85aff948-1893-4b24-9226-d00e66cb4f82",
    "sentence": "Uncertainty about the economic outlook has increased further. The Committee is attentive to the risks to both sides of its dual mandate and judges that the risks of higher unemployment and higher inflation have risen.",
    "source": "statement_20250507.txt",
    "doc_type": "statement",
    "date": "2025-05-07",
    "context_question": null,
    "top": "",
    "sen": "",
    "ten": "",
    "hor": "",
    "com": "",
    "ris": "",
    "wid": ""
  },
  {
    "id": "3cdb20b2-89fb-44f1-9281-249ff09ff9db",
    "sentence": "In view of realized and expected labor market conditions and inflation, the Committee decided to raise the target range for the federal funds rate to 2-1/4 to 2‑1/2 percent.",
    "source": "statement_20181219.txt",
    "doc_type": "statement",
    "date": "2018-12-19",
    "context_question": null,
    "top": "",
    "sen": "",
    "ten": "",
    "hor": "",
    "com": "",
    "ris": "",
    "wid": ""
  },
  {
    "id": "d3accf2c-044d-4f34-b107-1839010240cb",
    "sentence": "Although the near-term economic outlook is weak, the Committee anticipates that policy actions to stabilize financial markets and institutions, together with fiscal and monetary stimulus, will contribute to a gradual resumption of sustainable economic growth. In light of increasing economic slack here and abroad, the Committee expects that inflation will remain subdued. Moreover, the Committee sees some risk that inflation could persist for a time below rates that best foster economic growth and price stability in the longer term.",
    "source": "statement_20090318.txt",
    "doc_type": "statement",
    "date": "2009-03-18",
    "context_question": null,
    "top": "",
    "sen": "",
    "ten": "",
    "hor": "",
    "com": "",
    "ris": "",
    "wid": ""
  },
  {
    "id": "a319e774-95e8-4243-b71c-42acbe00c6e8",
    "sentence": "The anticipated expiration dates for the Term Asset-Backed Securities Loan Facility remain set at June 30 for loans backed by new-issue commercial mortgage-backed securities and March 31 for loans backed by all other types of collateral. The Federal Reserve is prepared to modify these plans if necessary to support financial stability and economic growth.",
    "source": "statement_20100127.txt",
    "doc_type": "statement",
    "date": "2010-01-27",
    "context_question": null,
    "top": "",
    "sen": "",
    "ten": "",
    "hor": "",
    "com": "",
    "ris": "",
    "wid": ""
  },
  {
    "id": "833bb068-1747-4e9a-8d9b-959fd174984b",
    "sentence": "The Committee will carefully monitor actual and expected inflation developments relative to its symmetric inflation goal. The Committee expects that economic conditions will evolve in a manner that will warrant further gradual increases in the federal funds rate; the federal funds rate is likely to remain, for some time, below levels that are expected to prevail in the longer run.",
    "source": "statement_20180502.txt",
    "doc_type": "statement",
    "date": "2018-05-02",
    "context_question": null,
    "top": "",
    "sen": "",
    "ten": "",
    "hor": "",
    "com": "",
    "ris": "",
    "wid": ""
  },
  {
    "id": "4a7580ff-f3a4-44d3-96cf-903318fb2808",
    "sentence": "In addition, the Committee will continue reducing its holdings of Treasury securities and agency debt and agency mortgage-backed securities, as described in the Plans for Reducing the Size of the Federal Reserve's Balance Sheet that were issued in May.",
    "source": "statement_20221214.txt",
    "doc_type": "statement",
    "date": "2022-12-14",
    "context_question": null,
    "top": "",
    "sen": "",
    "ten": "",
    "hor": "",
    "com": "",
    "ris": "",
    "wid": ""
  },
  {
    "id": "65cc9bf7-2109-4485-a293-4ffe21ae9cc3",
    "sentence": "In considering the extent and timing of additional adjustments to the target range for the federal funds rate, the Committee will carefully assess incoming data, the evolving outlook, and the balance of risks.",
    "source": "statement_20251210.txt",
    "doc_type": "statement",
    "date": "2025-12-10",
    "context_question": null,
    "top": "",
    "sen": "",
    "ten": "",
    "hor": "",
    "com": "",
    "ris": "",
    "wid": ""
  },
  {
    "id": "ae7a016d-5864-454c-9827-8c14c2d6bd0a",
    "sentence": "In determining how long to maintain a highly accommodative stance of monetary policy, the Committee will also consider other information, including additional measures of labor market conditions, indicators of inflation pressures and inflation expectations, and readings on financial developments.",
    "source": "statement_20131030.txt",
    "doc_type": "statement",
    "date": "2013-10-30",
    "context_question": null,
    "top": "",
    "sen": "",
    "ten": "",
    "hor": "",
    "com": "",
    "ris": "",
    "wid": ""
  },
  {
    "id": "ce7830bc-ea40-4f13-a4cb-1b387748c199",
    "sentence": "To promote the ongoing economic recovery and to help ensure that inflation, over time, is at levels consistent with its mandate, the Committee decided today to keep the target range for the federal funds rate at 0 to 1/4 percent. The Committee currently anticipates that economic conditions--including low rates of resource utilization and a subdued outlook for inflation over the medium run--are likely to warrant exceptionally low levels for the federal funds rate at least through mid-2013.",
    "source": "statement_20110809.txt",
    "doc_type": "statement",
    "date": "2011-08-09",
    "context_question": null,
    "top": "",
    "sen": "",
    "ten": "",
    "hor": "",
    "com": "",
    "ris": "",
    "wid": ""
  },
  {
    "id": "27f8edb0-0866-4629-9348-4074d3a21e0f",
    "sentence": "However, downside risks to growth remain.",
    "source": "statement_20080318.txt",
    "doc_type": "statement",
    "date": "2008-03-18",
    "context_question": null,
    "top": "",
    "sen": "",
    "ten": "",
    "hor": "",
    "com": "",
    "ris": "",
    "wid": ""
  },
  {
    "id": "47c1a9b7-0b8b-43ad-b14c-8d8dcd845cfb",
    "sentence": "Against this backdrop, the Committee decided to maintain the target range for the federal funds rate at 1/4 to 1/2 percent. The Committee judges that the case for an increase in the federal funds rate has strengthened but decided, for the time being, to wait for further evidence of continued progress toward its objectives.",
    "source": "statement_20160921.txt",
    "doc_type": "statement",
    "date": "2016-09-21",
    "context_question": null,
    "top": "",
    "sen": "",
    "ten": "",
    "hor": "",
    "com": "",
    "ris": "",
    "wid": ""
  },
  {
    "id": "36e023f0-9f09-4a4f-aa8d-703866a1eaea",
    "sentence": "As is the case with the current securities lending program, securities will be made available through an auction process.",
    "source": "statement_20080311.txt",
    "doc_type": "statement",
    "date": "2008-03-11",
    "context_question": null,
    "top": "",
    "sen": "",
    "ten": "",
    "hor": "",
    "com": "",
    "ris": "",
    "wid": ""
  },
  {
    "id": "46bf610b-0513-453c-86e2-792eef507ceb",
    "sentence": "The Committee is maintaining its existing policy of reinvesting principal payments from its holdings of agency debt and agency mortgage-backed securities in agency mortgage-backed securities and of rolling over maturing Treasury securities at auction. Taken together, these actions should maintain downward pressure on longer-term interest rates, support mortgage markets, and help to make broader financial conditions more accommodative, which in turn should promote a stronger economic recovery and help to ensure that inflation, over time, is at the rate most consistent with the Committee's dual mandate.",
    "source": "statement_20131030.txt",
    "doc_type": "statement",
    "date": "2013-10-30",
    "context_question": null,
    "top": "",
    "sen": "",
    "ten": "",
    "hor": "",
    "com": "",
    "ris": "",
    "wid": ""
  },
  {
    "id": "296bb697-28cb-4244-8bc3-cbcc380f1239",
    "sentence": "With inflation well above 2 percent and a strong labor market, the Committee expects it will soon be appropriate to raise the target range for the federal funds rate.",
    "source": "statement_20220126.txt",
    "doc_type": "statement",
    "date": "2022-01-26",
    "context_question": null,
    "top": "",
    "sen": "",
    "ten": "",
    "hor": "",
    "com": "",
    "ris": "",
    "wid": ""
  },
  {
    "id": "f3b5f7a6-118e-4117-b6bf-23c9c1f910be",
    "sentence": "The Committee is strongly committed to supporting maximum employment and returning inflation to its 2 percent objective.",
    "source": "statement_20251210.txt",
    "doc_type": "statement",
    "date": "2025-12-10",
    "context_question": null,
    "top": "",
    "sen": "",
    "ten": "",
    "hor": "",
    "com": "",
    "ris": "",
    "wid": ""
  },
  {
    "id": "4de41e81-9851-4266-b9af-c24a9c0cb59e",
    "sentence": "The Committee will continue its purchases of Treasury and agency mortgage-backed securities, and employ its other policy tools as appropriate, until the outlook for the labor market has improved substantially in a context of price stability.",
    "source": "statement_20130731.txt",
    "doc_type": "statement",
    "date": "2013-07-31",
    "context_question": null,
    "top": "",
    "sen": "",
    "ten": "",
    "hor": "",
    "com": "",
    "ris": "",
    "wid": ""
  },
  {
    "id": "6e1b74e3-6441-475c-846e-cd9930061eb9",
    "sentence": "In determining the timing and size of future adjustments to the target range for the federal funds rate, the Committee will assess realized and expected economic conditions relative to its objectives of maximum employment and 2 percent inflation. This assessment will take into account a wide range of information, including measures of labor market conditions, indicators of inflation pressures and inflation expectations, and readings on financial and international developments.",
    "source": "statement_20180502.txt",
    "doc_type": "statement",
    "date": "2018-05-02",
    "context_question": null,
    "top": "",
    "sen": "",
    "ten": "",
    "hor": "",
    "com": "",
    "ris": "",
    "wid": ""
  },
  {
    "id": "ba21376c-d517-417d-9349-53f270dcf6e5",
    "sentence": "The Federal Reserve is prepared to use its full range of tools to support the flow of credit to households and businesses and thereby promote its maximum employment and price stability goals. To support the smooth functioning of markets for Treasury securities and agency mortgage-backed securities that are central to the flow of credit to households and businesses, over coming months the Committee will increase its holdings of Treasury securities by at least $500 billion and its holdings of agency mortgage-backed securities by at least $200 billion.",
    "source": "statement_20200315.txt",
    "doc_type": "statement",
    "date": "2020-03-15",
    "context_question": null,
    "top": "",
    "sen": "",
    "ten": "",
    "hor": "",
    "com": "",
    "ris": "",
    "wid": ""
  },
  {
    "id": "fbe2cf40-f45c-4077-bf0d-842f2d433726",
    "sentence": "The Committee also will continue through the end of the year its program to extend the average maturity of its holdings of securities as announced in June, and it is maintaining its existing policy of reinvesting principal payments from its holdings of agency debt and agency mortgage-backed securities in agency mortgage-backed securities. These actions, which together will increase the Committee’s holdings of longer-term securities by about $85 billion each month through the end of the year, should put downward pressure on longer-term interest rates, support mortgage markets, and help to make broader financial conditions more accommodative.",
    "source": "statement_20120913.txt",
    "doc_type": "statement",
    "date": "2012-09-13",
    "context_question": null,
    "top": "",
    "sen": "",
    "ten": "",
    "hor": "",
    "com": "",
    "ris": "",
    "wid": ""
  },
  {
    "id": "2806e161-c35f-40ad-8d58-8bc236532e28",
    "sentence": "In addition, the Committee will continue reducing its holdings of Treasury securities and agency debt and agency mortgage-backed securities, as described in its previously announced plans.",
    "source": "statement_20240320.txt",
    "doc_type": "statement",
    "date": "2024-03-20",
    "context_question": null,
    "top": "",
    "sen": "",
    "ten": "",
    "hor": "",
    "com": "",
    "ris": "",
    "wid": ""
  },
  {
    "id": "a528cd70-9822-4d18-a735-e5331a850693",
    "sentence": "In judging when to moderate the pace of asset purchases, the Committee will, at its coming meetings, assess whether incoming information continues to support the Committee's expectation of ongoing improvement in labor market conditions and inflation moving back toward its longer-run objective.",
    "source": "statement_20131030.txt",
    "doc_type": "statement",
    "date": "2013-10-30",
    "context_question": null,
    "top": "",
    "sen": "",
    "ten": "",
    "hor": "",
    "com": "",
    "ris": "",
    "wid": ""
  },
  {
    "id": "a6248c91-bd55-44de-b461-cd69a59ebeeb",
    "sentence": "It will continue to assess the economic outlook in light of incoming information and is prepared to employ its tools as appropriate.",
    "source": "statement_20110921.txt",
    "doc_type": "statement",
    "date": "2011-09-21",
    "context_question": null,
    "top": "",
    "sen": "",
    "ten": "",
    "hor": "",
    "com": "",
    "ris": "",
    "wid": ""
  },
  {
    "id": "36250285-ec91-4833-a8d6-8e396d8d37d9",
    "sentence": "The Committee currently judges that there is sufficient underlying strength in the broader economy to support ongoing improvement in labor market conditions.",
    "source": "statement_20140917.txt",
    "doc_type": "statement",
    "date": "2014-09-17",
    "context_question": null,
    "top": "",
    "sen": "",
    "ten": "",
    "hor": "",
    "com": "",
    "ris": "",
    "wid": ""
  },
  {
    "id": "9885df4b-95e9-482b-9be9-9e2650f322dc",
    "sentence": "Since then, the economy has made progress toward these goals, and the Committee will continue to assess progress in coming meetings. These asset purchases help foster smooth market functioning and accommodative financial conditions, thereby supporting the flow of credit to households and businesses.",
    "source": "statement_20210728.txt",
    "doc_type": "statement",
    "date": "2021-07-28",
    "context_question": null,
    "top": "",
    "sen": "",
    "ten": "",
    "hor": "",
    "com": "",
    "ris": "",
    "wid": ""
  },
  {
    "id": "9005617f-94e5-43d7-8f63-5357a634e055",
    "sentence": "Against this backdrop, the Committee decided to maintain the target range for the federal funds rate at 1/4 to 1/2 percent. The Committee judges that the case for an increase in the federal funds rate has continued to strengthen but decided, for the time being, to wait for some further evidence of continued progress toward its objectives.",
    "source": "statement_20161102.txt",
    "doc_type": "statement",
    "date": "2016-11-02",
    "context_question": null,
    "top": "",
    "sen": "",
    "ten": "",
    "hor": "",
    "com": "",
    "ris": "",
    "wid": ""
  },
  {
    "id": "b0673f77-3638-4107-9714-f8f13a92a2f3",
    "sentence": "Conversely, if progress proves slower than expected, then increases in the target range are likely to occur later than currently anticipated.",
    "source": "statement_20150128.txt",
    "doc_type": "statement",
    "date": "2015-01-28",
    "context_question": null,
    "top": "",
    "sen": "",
    "ten": "",
    "hor": "",
    "com": "",
    "ris": "",
    "wid": ""
  },
  {
    "id": "e13871f6-2fcb-4884-80ee-5035b2e4e21d",
    "sentence": "In support of its goals, the Committee decided to maintain the target range for the federal funds rate at 4-1/4 to 4-1/2 percent.",
    "source": "statement_20250730.txt",
    "doc_type": "statement",
    "date": "2025-07-30",
    "context_question": null,
    "top": "",
    "sen": "",
    "ten": "",
    "hor": "",
    "com": "",
    "ris": "",
    "wid": ""
  },
  {
    "id": "79112fe2-cc2b-43bd-811d-d0f5c48353fe",
    "sentence": "Growth in consumer spending has slowed and labor markets have softened.",
    "source": "statement_20080318.txt",
    "doc_type": "statement",
    "date": "2008-03-18",
    "context_question": null,
    "top": "",
    "sen": "",
    "ten": "",
    "hor": "",
    "com": "",
    "ris": "",
    "wid": ""
  },
  {
    "id": "e4a1709b-2771-46a7-9292-fd3de40e4baa",
    "sentence": "The Committee is maintaining its existing policy of reinvesting principal payments from its holdings of agency debt and agency mortgage-backed securities in agency mortgage-backed securities.",
    "source": "statement_20120620.txt",
    "doc_type": "statement",
    "date": "2012-06-20",
    "context_question": null,
    "top": "",
    "sen": "",
    "ten": "",
    "hor": "",
    "com": "",
    "ris": "",
    "wid": ""
  },
  {
    "id": "15e182b5-edd2-456c-9c0e-543819cfa54d",
    "sentence": "In view of realized and expected labor market conditions and inflation, the Committee decided to raise the target range for the federal funds rate to 1-3/4 to 2 percent.",
    "source": "statement_20180613.txt",
    "doc_type": "statement",
    "date": "2018-06-13",
    "context_question": null,
    "top": "",
    "sen": "",
    "ten": "",
    "hor": "",
    "com": "",
    "ris": "",
    "wid": ""
  },
  {
    "id": "b3ea7cae-5a1e-4c26-a5d7-c27e471a82db",
    "sentence": "If the outlook for the labor market does not improve substantially, the Committee will continue its purchases of Treasury and agency mortgage-backed securities, and employ its other policy tools as appropriate, until such improvement is achieved in a context of price stability.",
    "source": "statement_20130130.txt",
    "doc_type": "statement",
    "date": "2013-01-30",
    "context_question": null,
    "top": "",
    "sen": "",
    "ten": "",
    "hor": "",
    "com": "",
    "ris": "",
    "wid": ""
  },
  {
    "id": "df60b21e-5bf2-4aba-acdc-91b20f51af21",
    "sentence": "However, if incoming information indicates faster progress toward the Committee’s employment and inflation objectives than the Committee now expects, then increases in the target range for the federal funds rate are likely to occur sooner than currently anticipated.",
    "source": "statement_20150128.txt",
    "doc_type": "statement",
    "date": "2015-01-28",
    "context_question": null,
    "top": "",
    "sen": "",
    "ten": "",
    "hor": "",
    "com": "",
    "ris": "",
    "wid": ""
  },
  {
    "id": "cdac36c4-6a81-46b6-9417-e91ec08889cb",
    "sentence": "To support continued progress toward maximum employment and price stability, the Committee today reaffirmed its view that a highly accommodative stance of monetary policy remains appropriate.",
    "source": "statement_20140917.txt",
    "doc_type": "statement",
    "date": "2014-09-17",
    "context_question": null,
    "top": "",
    "sen": "",
    "ten": "",
    "hor": "",
    "com": "",
    "ris": "",
    "wid": ""
  },
  {
    "id": "2e34a166-4c9a-4924-a4de-c6d2448b4b7b",
    "sentence": "The Committee will continue to monitor carefully the size and composition of the Federal Reserve's balance sheet in light of evolving financial market developments and to assess whether expansions of or modifications to lending facilities would serve to further support credit markets and economic activity and help to preserve price stability.",
    "source": "statement_20090128.txt",
    "doc_type": "statement",
    "date": "2009-01-28",
    "context_question": null,
    "top": "",
    "sen": "",
    "ten": "",
    "hor": "",
    "com": "",
    "ris": "",
    "wid": ""
  },
  {
    "id": "8b422efe-e90b-470a-a0a0-6401374f0ae4",
    "sentence": "The Committee discussed the range of policy tools available to promote a stronger economic recovery in a context of price stability. It will continue to assess the economic outlook in light of incoming information and is prepared to employ these tools as appropriate.",
    "source": "statement_20110809.txt",
    "doc_type": "statement",
    "date": "2011-08-09",
    "context_question": null,
    "top": "",
    "sen": "",
    "ten": "",
    "hor": "",
    "com": "",
    "ris": "",
    "wid": ""
  },
  {
    "id": "b25cea18-7ff8-48fa-8853-0970afa8aa87",
    "sentence": "The Committee will continue its purchases of Treasury and agency mortgage-backed securities, and employ its other policy tools as appropriate, until the outlook for the labor market has improved substantially in a context of price stability. In determining the size, pace, and composition of its asset purchases, the Committee will continue to take appropriate account of the likely efficacy and costs of such purchases as well as the extent of progress toward its economic objectives.",
    "source": "statement_20130320.txt",
    "doc_type": "statement",
    "date": "2013-03-20",
    "context_question": null,
    "top": "",
    "sen": "",
    "ten": "",
    "hor": "",
    "com": "",
    "ris": "",
    "wid": ""
  },
  {
    "id": "9f55ffa8-3c68-477d-b129-9d3e63190d32",
    "sentence": "The Committee remains highly attentive to inflation risks.",
    "source": "statement_20230322.txt",
    "doc_type": "statement",
    "date": "2023-03-22",
    "context_question": null,
    "top": "",
    "sen": "",
    "ten": "",
    "hor": "",
    "com": "",
    "ris": "",
    "wid": ""
  }
]